test_autozz/__init__.py
test_autozz/core.py
test_autozz/log.py
test_autozz/server.py
test_autozz-0.1.1.dist-info/METADATA
test_autozz-0.1.1.dist-info/WHEEL
test_autozz-0.1.1.dist-info/top_level.txt
test_autozz-0.1.1.dist-info/RECORD
